common/__init__.py
common/automobile/auto_expense.py
common/business/business_information.py
common/business/business_invoice.py
common/business/dependency_info.py
common/business/home_office.py
common/business/meal_allowance.py
common/business/operating_expenses.py
common/business/travel_expense.py
common/dependent/dependent_financial_information.py
common/dependent/dependent_info.py
common/dependent/dependent_living_arrangement.py
common/dependent/dependent_relationship_details.py
common/dependent/dependent_relationship_info.py
common/dependent/dependents.py
common/dependent/child/dependent_child_care_information.py
common/dependent/child/dependent_child_custody_info.py
common/dependent/child/dependent_child_support_payments.py
common/dependent/spouse/dependent_marital_status.py
common/dependent/spouse/dependent_spouse_info.py
common/education/education_credits.py
common/education/education_enrolment_info.py
common/education/education_expenses.py
common/education/education_forms.py
common/education/education_info.py
common/education/education_tuition_info.py
common/education/status_info.py
common/employment/employee_info.py
common/employment/employer_info.py
common/financial/bankruptcy_info.py
common/financial/financial_asset_liablilities.py
common/financial/financial_contributions.py
common/financial/financial_eligibility_info.py
common/financial/financial_expense_info.py
common/financial/financial_foreign_income_info.py
common/financial/financial_income_info.py
common/financial/financial_info.py
common/financial/financial_summary.py
common/info/address_info.py
common/info/compliance_info.py
common/info/contact_info.py
common/info/disability_info.py
common/info/identification_info.py
common/info/personal_info.py
common/info/preferences_info.py
common/info/review_info.py
common/info/tax_info.py
common/medical/medical_disability_info.py
common/medical/medical_expenses.py
common/medical/medical_info.py
common/medical/medical_practioner_info.py
tax_commons-0.1.0.dist-info/METADATA
tax_commons-0.1.0.dist-info/WHEEL
tax_commons-0.1.0.dist-info/top_level.txt
tax_commons-0.1.0.dist-info/RECORD
